lafv/__init__.py
lafv/views.py
drf_lafv-0.0.2.dist-info/RECORD
drf_lafv-0.0.2.dist-info/top_level.txt
drf_lafv-0.0.2.dist-info/DESCRIPTION.rst
drf_lafv-0.0.2.dist-info/metadata.json
drf_lafv-0.0.2.dist-info/WHEEL
drf_lafv-0.0.2.dist-info/METADATA
