Metadata-Version: 2.0
Name: drf-lafv
Version: 0.0.2
Summary: A better way than DRF proposed for do some basic filters
Home-page: https://github.com/angvp/drf-lafv
Author: Angel Velasquez
Author-email: angvp@archlinux.org
License: BSD
Platform: UNKNOWN
Classifier: Development Status :: 2 - Pre-Alpha
Classifier: Environment :: Web Environment
Classifier: Framework :: Django
Classifier: Intended Audience :: Developers
Classifier: License :: OSI Approved :: BSD License
Classifier: Operating System :: OS Independent
Classifier: Natural Language :: English
Classifier: Programming Language :: Python :: 2
Classifier: Programming Language :: Python :: 2.7
Classifier: Programming Language :: Python :: 3
Classifier: Programming Language :: Python :: 3.3
Classifier: Programming Language :: Python :: 3.4
Classifier: Programming Language :: Python :: 3.5
Classifier: Topic :: Internet :: WWW/HTTP
